spindynamics/__init__.py
spindynamics/client.py
spindynamics/exceptions.py
spindynamics/py.typed
spindynamics/resources.py
spindynamics/types.py
spindynamics-0.3.1.dist-info/METADATA
spindynamics-0.3.1.dist-info/WHEEL
spindynamics-0.3.1.dist-info/licenses/LICENSE
spindynamics-0.3.1.dist-info/RECORD
