Metadata-Version: 2.4
Name: spindynamics
Version: 0.3.1
Summary: Python SDK for the SpinDynamics inference routing platform
Project-URL: Homepage, https://spindynamics.net
Project-URL: Documentation, https://spindynamics.net/docs
Project-URL: Repository, https://github.com/spindynamics/sdk-python
License-Expression: Apache-2.0
License-File: LICENSE
Requires-Python: >=3.9
Requires-Dist: build>=1.4.0
Requires-Dist: httpx>=0.24.0
Requires-Dist: twine>=6.2.0
